Metadata-Version: 2.1
Name: flake8-checker
Version: 0.0.2
Summary: Plugin to comply with my picky standards
Home-page: UNKNOWN
Author: Harish, Dasika
Author-email: harish.dasika@gmail.com
License: UNKNOWN
Platform: UNKNOWN
Classifier: Development Status :: 3 - Alpha
Requires-Python: >=3.5
